backle/__init__.py
backle/_version.py
backle/core.py
backle/data_factory.py
backle/environment.py
backle-0.0.2.dev13.dist-info/LICENSE
backle-0.0.2.dev13.dist-info/METADATA
backle-0.0.2.dev13.dist-info/WHEEL
backle-0.0.2.dev13.dist-info/top_level.txt
backle-0.0.2.dev13.dist-info/RECORD
