Metadata-Version: 2.1
Name: backle
Version: 0.0.2.dev13
Author: Scott Caratozzolo
License: MIT License
Project-URL: homepage, https://github.com/scaratozzolo/backle
Project-URL: repository, https://github.com/scaratozzolo/backle
Classifier: Development Status :: 4 - Beta
Classifier: License :: OSI Approved :: MIT License
Classifier: Natural Language :: English
Classifier: Programming Language :: Python
Classifier: Programming Language :: Python :: 3
Classifier: Programming Language :: Python :: 3 :: Only
Classifier: Programming Language :: Python :: 3.8
Classifier: Programming Language :: Python :: 3.9
Classifier: Programming Language :: Python :: 3.10
Classifier: Programming Language :: Python :: 3.11
Classifier: Operating System :: OS Independent
Classifier: Intended Audience :: Science/Research
Classifier: Topic :: Office/Business :: Financial :: Investment
Classifier: Topic :: Scientific/Engineering :: Information Analysis
Requires-Python: >=3.8
License-File: LICENSE
Requires-Dist: pandas (>=1.4.0)
Requires-Dist: yfinance (>=0.2.4)
Requires-Dist: pandas-market-calendars (>=4.1.3)
Requires-Dist: tqdm (>=4.64.1)
Requires-Dist: pytz (>=2022.7.1)
Requires-Dist: loguru (>=0.6.0)
Requires-Dist: pyfolio-reloaded (>=0.9.5)
Requires-Dist: quantstats (>=0.0.59)
